.coveragerc
.travis.yml
AUTHORS
ChangeLog
LICENSE
README.md
pyproject.toml
requirements-dev.txt
requirements.txt
setup.cfg
setup.py
hlog/__init__.py
hlog.egg-info/PKG-INFO
hlog.egg-info/SOURCES.txt
hlog.egg-info/dependency_links.txt
hlog.egg-info/not-zip-safe
hlog.egg-info/pbr.json
hlog.egg-info/requires.txt
hlog.egg-info/top_level.txt
tests/test_integration.py
tests/test_log_entries.py
tests/test_logger.py