Metadata-Version: 2.1
Name: hlog
Version: 1.0.1
Summary: Hash-chain log implementation
Home-page: UNKNOWN
Author: Eric Gazoni
Author-email: eric@adimian.com
License: UNKNOWN
Platform: UNKNOWN
Classifier: Development Status :: 4 - Beta
Classifier: Operating System :: POSIX
Classifier: Programming Language :: Python
Classifier: Programming Language :: Python :: 3.6
Classifier: Programming Language :: Python :: 3.7
